luxcorerender_opencl-2.0a5.data/purelib/pyluxcore/__init__.py
luxcorerender_opencl-2.0a5.data/purelib/pyluxcore/libembree.so.2
luxcorerender_opencl-2.0a5.data/purelib/pyluxcore/libtbb.so.2
luxcorerender_opencl-2.0a5.data/purelib/pyluxcore/libtbbmalloc.so.2
luxcorerender_opencl-2.0a5.data/purelib/pyluxcore/pyluxcore.so
luxcorerender_opencl-2.0a5.data/purelib/pyluxcoretools/__init__.py
luxcorerender_opencl-2.0a5.data/purelib/pyluxcoretools/pyluxcoreconsole/__init__.py
luxcorerender_opencl-2.0a5.data/purelib/pyluxcoretools/pyluxcoreconsole/cmd.py
luxcorerender_opencl-2.0a5.data/purelib/pyluxcoretools/pyluxcoremerge/__init__.py
luxcorerender_opencl-2.0a5.data/purelib/pyluxcoretools/pyluxcoremerge/cmd.py
luxcorerender_opencl-2.0a5.data/purelib/pyluxcoretools/pyluxcorenetconsole/__init__.py
luxcorerender_opencl-2.0a5.data/purelib/pyluxcoretools/pyluxcorenetconsole/cmd.py
luxcorerender_opencl-2.0a5.data/purelib/pyluxcoretools/pyluxcorenetnode/__init__.py
luxcorerender_opencl-2.0a5.data/purelib/pyluxcoretools/pyluxcorenetnode/cmd.py
luxcorerender_opencl-2.0a5.data/purelib/pyluxcoretools/renderfarm/__init__.py
luxcorerender_opencl-2.0a5.data/purelib/pyluxcoretools/renderfarm/renderfarm.py
luxcorerender_opencl-2.0a5.data/purelib/pyluxcoretools/renderfarm/renderfarmfilmmerger.py
luxcorerender_opencl-2.0a5.data/purelib/pyluxcoretools/renderfarm/renderfarmjobsingleimage.py
luxcorerender_opencl-2.0a5.data/purelib/pyluxcoretools/renderfarm/renderfarmnode.py
luxcorerender_opencl-2.0a5.data/purelib/pyluxcoretools/utils/__init__.py
luxcorerender_opencl-2.0a5.data/purelib/pyluxcoretools/utils/args.py
luxcorerender_opencl-2.0a5.data/purelib/pyluxcoretools/utils/filesystem.py
luxcorerender_opencl-2.0a5.data/purelib/pyluxcoretools/utils/loghandler.py
luxcorerender_opencl-2.0a5.data/purelib/pyluxcoretools/utils/md5.py
luxcorerender_opencl-2.0a5.data/purelib/pyluxcoretools/utils/netbeacon.py
luxcorerender_opencl-2.0a5.data/purelib/pyluxcoretools/utils/socket.py
luxcorerender_opencl-2.0a5.dist-info/DESCRIPTION.rst
luxcorerender_opencl-2.0a5.dist-info/METADATA
luxcorerender_opencl-2.0a5.dist-info/RECORD
luxcorerender_opencl-2.0a5.dist-info/WHEEL
luxcorerender_opencl-2.0a5.dist-info/metadata.json
luxcorerender_opencl-2.0a5.dist-info/top_level.txt
